vrame/__init__.py
vrame/_column_types_validation.py
vrame/_column_validation.py
vrame/basemodel.py
vrame/column_types.py
vrame/error.py
Vrame-1.0.3.dist-info/LICENSE.txt
Vrame-1.0.3.dist-info/METADATA
Vrame-1.0.3.dist-info/WHEEL
Vrame-1.0.3.dist-info/top_level.txt
Vrame-1.0.3.dist-info/RECORD
