Metadata-Version: 2.1
Name: Vrame
Version: 1.0.3
Summary: Efficiently parse and validate all columns in pandas DataFrame.
Author-email: Yuen Shing Yan Hindy <yuenshingyan@gmail.com>
Project-URL: Homepage, https://github.com/yuenshingyan/Vrame
Project-URL: Issues, https://github.com/yuenshingyan/Vrame/issues
Keywords: pandas,pd,dataframe,df,validation,validate,parsing,parse,pydantic,Pydantic,effcient,effciently
Classifier: Programming Language :: Python :: 3
Classifier: License :: OSI Approved :: MIT License
Classifier: Operating System :: OS Independent
Requires-Python: >=3.10
License-File: LICENSE.txt
